{
  "currentSong": {
    "title": "herkes gibisin",
    "artist": "Semicenk",
    "audioUrl": "https://dl.musicdel.ir/Music/1401/03/semicenk_herkes_gibisin.mp3",
    "coverUrl": "https://musicdel.ir/wp-content/uploads/2022/07/herkesgibisin.jpg",
    "lyrics": "Her şey bitermiş zamanla\nİçinde kalmasın, söyle, bilelim\nBana layık soğuk vedansa\nUnuttum artık, herkes gibisin\nHer şey bitermiş zamanla\nİçinde kalmasın, söyle, bilelim\nBana layık soğuk vedansa\nUnuttum artık, herkes gibisin\nNe ara bu duruma düştük?\nSaftı gönlüm, çabuk kaçtı elimden\nBoşa geçti, gördüm\nÖmrümden çaldığın o günler\nKırıkları vardır elbet\nYaşamın bi' parçasıydı her şey\nUmut edip anılanlar, yakılanlar\nYıkılanlar\nFaydası yok sözlerin\nHer nefeste başa sarar özlemin\nBeni yoran bu kasveti\nTutamadım, erken çözüldü dizlerim\nHer şey bitermiş zamanla\nİçinde kalmasın, söyle, bilelim\nBana layık soğuk vedansa\nUnuttum artık, herkes gibisin\nHer şey bitermiş zamanla\nİçinde kalmasın, söyle, bilelim\nBana layık soğuk vedansa\nUnuttum artık, herkes gibisin\nHer şey bitermiş zamanla\nİçinde kalmasın, söyle, bilelim\nBana layık soğuk vedansa\nUnuttum artık, herkes gibisin\nNe ara bu duruma düştük?\nSaftı gönlüm, çabuk kaçtı elimden\nBoşa geçti, gördüm\nÖmrümden çaldığın o günler\nKırıkları vardır elbet\nYaşamın bi' parçasıydı her şey\nUmut edip anılanlar, yakılanlar\nYıkılanlar\nFaydası yok sözlerin\nHer nefeste başa sarar özlemin\nBeni yoran bu kasveti\nTutamadım, erken çözüldü dizlerim\nHer şey bitermiş zamanla\nİçinde kalmasın, söyle, bilelim\nBana layık soğuk vedansa\nUnuttum artık, herkes gibisin\nHer şey bitermiş zamanla\nİçinde kalmasın, söyle, bilelim\nBana layık soğuk vedansa\nUnuttum artık, herkes gibisin"
  }
}
